defusedivision/__init__.py
defusedivision/concurrency.py
defusedivision/entrypoint.py
defusedivision/game.py
defusedivision/net.py
defusedivision/client/__init__.py
defusedivision/client/client.py
defusedivision/client/test_client.py
defusedivision/minesweeper/__init__.py
defusedivision/minesweeper/cell.py
defusedivision/minesweeper/contents.py
defusedivision/minesweeper/minefield.py
defusedivision/minesweeper/test_cell.py
defusedivision/server/__init__.py
defusedivision/server/server.py
defusedivision/sound/29275__junggle__btn095.wav
defusedivision/sound/29301__junggle__btn121.wav
defusedivision/sound/321910__bboyjoe-15__you-lose.wav
defusedivision/sound/321917__bboyjoe-15__you-win.wav
defusedivision/sound/80401__steveygos93__explosion2.wav
defusedivision/sound/__init__.py
defusedivision/sound/sound.py
defusedivision/termclient/__init__.py
defusedivision/termclient/curses_colors.py
defusedivision/termclient/display.py
defusedivision/termclient/instance_setup.py
defusedivision/termclient/termclient.py
defusedivision/termclient/ui.py
defusedivision/termclient/menus/__init__.py
defusedivision/termclient/menus/mainmenu.py
defusedivision/termclient/menus/multiplayer.py
defusedivision-0.0.10.dist-info/DESCRIPTION.rst
defusedivision-0.0.10.dist-info/LICENSE.txt
defusedivision-0.0.10.dist-info/METADATA
defusedivision-0.0.10.dist-info/RECORD
defusedivision-0.0.10.dist-info/WHEEL
defusedivision-0.0.10.dist-info/entry_points.txt
defusedivision-0.0.10.dist-info/metadata.json
defusedivision-0.0.10.dist-info/top_level.txt
