Metadata-Version: 2.0
Name: defusedivision
Version: 0.0.10
Summary: Terminal based multiplayer (and singleplayer) minesweeper
Home-page: https://github.com/lelandbatey/defuse_division
Author: Leland Batey
Author-email: lelandbatey@lelandbatey.com
License: GPLv3
Platform: UNKNOWN
Classifier: Topic :: Games/Entertainment
Classifier: Topic :: Games/Entertainment :: Puzzle Games
Classifier: Programming Language :: Python :: 3
Requires-Dist: zeroconf
